COPYING
README
setup.py
signedheaders/__init__.py
signedheaders/secret.txt
signedheaders/test.py
signedheaders.egg-info/PKG-INFO
signedheaders.egg-info/SOURCES.txt
signedheaders.egg-info/dependency_links.txt
signedheaders.egg-info/entry_points.txt
signedheaders.egg-info/not-zip-safe
signedheaders.egg-info/top_level.txt