Metadata-Version: 1.0
Name: signedheaders
Version: 0.1
Summary: OpenCore signed headers
Home-page: UNKNOWN
Author: David Turner
Author-email: opencore-dev at lists.coactivate.org
License: GPLv3 or any later version
Platform: UNKNOWN
